{
  "file": "/home/ubuntu/checker-framework/checker/tests/index/ObjectClone.java",
  "predictions": [
    {
      "line": 27,
      "annotation_type": "@Positive",
      "confidence": 0.5486738085746765,
      "reason": "positive value expected (predicted by ENHANCED_CAUSAL model with 0.549 confidence)",
      "model_type": "enhanced_causal",
      "features": [
        0.0,
        0.0,
        0.0,
        0.0,
        0.0
      ]
    },
    {
      "line": 26,
      "annotation_type": "@Positive",
      "confidence": 0.5487562417984009,
      "reason": "positive value expected (predicted by ENHANCED_CAUSAL model with 0.549 confidence)",
      "model_type": "enhanced_causal",
      "features": [
        0.0,
        0.0,
        0.0,
        0.0,
        0.0
      ]
    },
    {
      "line": 25,
      "annotation_type": "@Positive",
      "confidence": 0.5488420128822327,
      "reason": "positive value expected (predicted by ENHANCED_CAUSAL model with 0.549 confidence)",
      "model_type": "enhanced_causal",
      "features": [
        0.0,
        0.0,
        0.0,
        0.0,
        0.0
      ]
    },
    {
      "line": 24,
      "annotation_type": "@Positive",
      "confidence": 0.5535740852355957,
      "reason": "positive value expected (predicted by ENHANCED_CAUSAL model with 0.554 confidence)",
      "model_type": "enhanced_causal",
      "features": [
        0.0,
        0.0,
        0.0,
        0.0,
        0.0
      ]
    },
    {
      "line": 23,
      "annotation_type": "@Positive",
      "confidence": 0.5573404431343079,
      "reason": "positive value expected (predicted by ENHANCED_CAUSAL model with 0.557 confidence)",
      "model_type": "enhanced_causal",
      "features": [
        0.0,
        0.0,
        0.0,
        0.0,
        1.0
      ]
    },
    {
      "line": 22,
      "annotation_type": "@Positive",
      "confidence": 0.5551139712333679,
      "reason": "positive value expected (predicted by ENHANCED_CAUSAL model with 0.555 confidence)",
      "model_type": "enhanced_causal",
      "features": [
        0.0,
        0.0,
        0.0,
        0.0,
        1.0
      ]
    },
    {
      "line": 21,
      "annotation_type": "@Positive",
      "confidence": 0.5550857782363892,
      "reason": "positive value expected (predicted by ENHANCED_CAUSAL model with 0.555 confidence)",
      "model_type": "enhanced_causal",
      "features": [
        0.0,
        0.0,
        0.0,
        0.0,
        1.0
      ]
    },
    {
      "line": 20,
      "annotation_type": "@Positive",
      "confidence": 0.5469903349876404,
      "reason": "positive value expected (predicted by ENHANCED_CAUSAL model with 0.547 confidence)",
      "model_type": "enhanced_causal",
      "features": [
        0.0,
        0.0,
        0.0,
        0.0,
        0.0
      ]
    },
    {
      "line": 19,
      "annotation_type": "@Positive",
      "confidence": 0.5572942495346069,
      "reason": "positive value expected (predicted by ENHANCED_CAUSAL model with 0.557 confidence)",
      "model_type": "enhanced_causal",
      "features": [
        0.0,
        0.0,
        0.0,
        0.0,
        0.0
      ]
    },
    {
      "line": 18,
      "annotation_type": "@Positive",
      "confidence": 0.5588102340698242,
      "reason": "positive value expected (predicted by ENHANCED_CAUSAL model with 0.559 confidence)",
      "model_type": "enhanced_causal",
      "features": [
        0.0,
        0.0,
        0.0,
        0.0,
        0.0
      ]
    },
    {
      "line": 17,
      "annotation_type": "@Positive",
      "confidence": 0.5572888255119324,
      "reason": "positive value expected (predicted by ENHANCED_CAUSAL model with 0.557 confidence)",
      "model_type": "enhanced_causal",
      "features": [
        0.0,
        0.0,
        0.0,
        0.0,
        0.0
      ]
    },
    {
      "line": 16,
      "annotation_type": "@Positive",
      "confidence": 0.5580335259437561,
      "reason": "positive value expected (predicted by ENHANCED_CAUSAL model with 0.558 confidence)",
      "model_type": "enhanced_causal",
      "features": [
        0.0,
        0.0,
        0.0,
        0.0,
        1.0
      ]
    },
    {
      "line": 15,
      "annotation_type": "@Positive",
      "confidence": 0.5526965260505676,
      "reason": "positive value expected (predicted by ENHANCED_CAUSAL model with 0.553 confidence)",
      "model_type": "enhanced_causal",
      "features": [
        0.0,
        0.0,
        0.0,
        0.0,
        1.0
      ]
    },
    {
      "line": 13,
      "annotation_type": "@Positive",
      "confidence": 0.5501638054847717,
      "reason": "positive value expected (predicted by ENHANCED_CAUSAL model with 0.550 confidence)",
      "model_type": "enhanced_causal",
      "features": [
        0.0,
        0.0,
        0.0,
        0.0,
        0.0
      ]
    },
    {
      "line": 12,
      "annotation_type": "@Positive",
      "confidence": 0.553938627243042,
      "reason": "positive value expected (predicted by ENHANCED_CAUSAL model with 0.554 confidence)",
      "model_type": "enhanced_causal",
      "features": [
        0.0,
        0.0,
        0.0,
        0.0,
        1.0
      ]
    },
    {
      "line": 11,
      "annotation_type": "@Positive",
      "confidence": 0.5534577369689941,
      "reason": "positive value expected (predicted by ENHANCED_CAUSAL model with 0.553 confidence)",
      "model_type": "enhanced_causal",
      "features": [
        0.0,
        0.0,
        0.0,
        0.0,
        1.0
      ]
    },
    {
      "line": 10,
      "annotation_type": "@Positive",
      "confidence": 0.5553964376449585,
      "reason": "positive value expected (predicted by ENHANCED_CAUSAL model with 0.555 confidence)",
      "model_type": "enhanced_causal",
      "features": [
        0.0,
        0.0,
        0.0,
        0.0,
        0.0
      ]
    },
    {
      "line": 9,
      "annotation_type": "@Positive",
      "confidence": 0.5579687356948853,
      "reason": "positive value expected (predicted by ENHANCED_CAUSAL model with 0.558 confidence)",
      "model_type": "enhanced_causal",
      "features": [
        0.0,
        0.0,
        0.0,
        0.0,
        0.0
      ]
    },
    {
      "line": 8,
      "annotation_type": "@Positive",
      "confidence": 0.5537890195846558,
      "reason": "positive value expected (predicted by ENHANCED_CAUSAL model with 0.554 confidence)",
      "model_type": "enhanced_causal",
      "features": [
        0.0,
        0.0,
        0.0,
        0.0,
        1.0
      ]
    },
    {
      "line": 6,
      "annotation_type": "@Positive",
      "confidence": 0.552055299282074,
      "reason": "positive value expected (predicted by ENHANCED_CAUSAL model with 0.552 confidence)",
      "model_type": "enhanced_causal",
      "features": [
        0.0,
        0.0,
        0.0,
        0.0,
        0.0
      ]
    },
    {
      "line": 4,
      "annotation_type": "@Positive",
      "confidence": 0.5577829480171204,
      "reason": "positive value expected (predicted by ENHANCED_CAUSAL model with 0.558 confidence)",
      "model_type": "enhanced_causal",
      "features": [
        0.0,
        0.0,
        0.0,
        0.0,
        0.0
      ]
    },
    {
      "line": 3,
      "annotation_type": "@Positive",
      "confidence": 0.5578432679176331,
      "reason": "positive value expected (predicted by ENHANCED_CAUSAL model with 0.558 confidence)",
      "model_type": "enhanced_causal",
      "features": [
        0.0,
        0.0,
        0.0,
        0.0,
        0.0
      ]
    }
  ],
  "timestamp": "2025-09-29 06:47:47"
}