{
  "file": "/home/ubuntu/checker-framework/checker/tests/index/annotated-jdk/src/java.base/share/classes/java/io/ObjectInput.java",
  "predictions": [
    {
      "line": 57,
      "annotation_type": "@NonNegative",
      "confidence": 0.5393510460853577,
      "reason": "non-negative value expected (predicted by ENHANCED_CAUSAL model with 0.539 confidence)",
      "model_type": "enhanced_causal",
      "features": [
        0.0,
        0.0,
        0.0,
        0.0,
        0.0
      ]
    },
    {
      "line": 56,
      "annotation_type": "@Positive",
      "confidence": 0.5390238761901855,
      "reason": "positive value expected (predicted by ENHANCED_CAUSAL model with 0.539 confidence)",
      "model_type": "enhanced_causal",
      "features": [
        0.0,
        0.0,
        0.0,
        0.0,
        1.0
      ]
    },
    {
      "line": 54,
      "annotation_type": "@Positive",
      "confidence": 0.5408669710159302,
      "reason": "positive value expected (predicted by ENHANCED_CAUSAL model with 0.541 confidence)",
      "model_type": "enhanced_causal",
      "features": [
        0.0,
        0.0,
        0.0,
        0.0,
        1.0
      ]
    },
    {
      "line": 53,
      "annotation_type": "@Positive",
      "confidence": 0.5393776893615723,
      "reason": "positive value expected (predicted by ENHANCED_CAUSAL model with 0.539 confidence)",
      "model_type": "enhanced_causal",
      "features": [
        0.0,
        0.0,
        0.0,
        0.0,
        0.0
      ]
    },
    {
      "line": 51,
      "annotation_type": "@Positive",
      "confidence": 0.5421713590621948,
      "reason": "positive value expected (predicted by ENHANCED_CAUSAL model with 0.542 confidence)",
      "model_type": "enhanced_causal",
      "features": [
        0.0,
        0.0,
        0.0,
        0.0,
        1.0
      ]
    },
    {
      "line": 50,
      "annotation_type": "@Positive",
      "confidence": 0.5392996072769165,
      "reason": "positive value expected (predicted by ENHANCED_CAUSAL model with 0.539 confidence)",
      "model_type": "enhanced_causal",
      "features": [
        0.0,
        0.0,
        0.0,
        0.0,
        0.0
      ]
    },
    {
      "line": 48,
      "annotation_type": "@Positive",
      "confidence": 0.5554794073104858,
      "reason": "positive value expected (predicted by ENHANCED_CAUSAL model with 0.555 confidence)",
      "model_type": "enhanced_causal",
      "features": [
        0.0,
        0.0,
        0.0,
        0.0,
        1.0
      ]
    },
    {
      "line": 47,
      "annotation_type": "@Positive",
      "confidence": 0.5391804575920105,
      "reason": "positive value expected (predicted by ENHANCED_CAUSAL model with 0.539 confidence)",
      "model_type": "enhanced_causal",
      "features": [
        0.0,
        0.0,
        0.0,
        0.0,
        0.0
      ]
    },
    {
      "line": 46,
      "annotation_type": "@Positive",
      "confidence": 0.5413235425949097,
      "reason": "positive value expected (predicted by ENHANCED_CAUSAL model with 0.541 confidence)",
      "model_type": "enhanced_causal",
      "features": [
        0.0,
        0.0,
        0.0,
        0.0,
        1.0
      ]
    },
    {
      "line": 45,
      "annotation_type": "@Positive",
      "confidence": 0.5390962362289429,
      "reason": "positive value expected (predicted by ENHANCED_CAUSAL model with 0.539 confidence)",
      "model_type": "enhanced_causal",
      "features": [
        0.0,
        0.0,
        0.0,
        0.0,
        0.0
      ]
    },
    {
      "line": 43,
      "annotation_type": "@Positive",
      "confidence": 0.5427206754684448,
      "reason": "positive value expected (predicted by ENHANCED_CAUSAL model with 0.543 confidence)",
      "model_type": "enhanced_causal",
      "features": [
        0.0,
        0.0,
        0.0,
        0.0,
        1.0
      ]
    },
    {
      "line": 42,
      "annotation_type": "@Positive",
      "confidence": 0.5412530303001404,
      "reason": "positive value expected (predicted by ENHANCED_CAUSAL model with 0.541 confidence)",
      "model_type": "enhanced_causal",
      "features": [
        0.0,
        0.0,
        0.0,
        0.0,
        1.0
      ]
    },
    {
      "line": 41,
      "annotation_type": "@Positive",
      "confidence": 0.5389819145202637,
      "reason": "positive value expected (predicted by ENHANCED_CAUSAL model with 0.539 confidence)",
      "model_type": "enhanced_causal",
      "features": [
        0.0,
        0.0,
        0.0,
        0.0,
        0.0
      ]
    },
    {
      "line": 39,
      "annotation_type": "@Positive",
      "confidence": 0.5404608845710754,
      "reason": "positive value expected (predicted by ENHANCED_CAUSAL model with 0.540 confidence)",
      "model_type": "enhanced_causal",
      "features": [
        0.0,
        0.0,
        0.0,
        0.0,
        1.0
      ]
    },
    {
      "line": 37,
      "annotation_type": "@Positive",
      "confidence": 0.5398722290992737,
      "reason": "positive value expected (predicted by ENHANCED_CAUSAL model with 0.540 confidence)",
      "model_type": "enhanced_causal",
      "features": [
        0.0,
        0.0,
        0.0,
        0.0,
        1.0
      ]
    },
    {
      "line": 35,
      "annotation_type": "@Positive",
      "confidence": 0.5413913726806641,
      "reason": "positive value expected (predicted by ENHANCED_CAUSAL model with 0.541 confidence)",
      "model_type": "enhanced_causal",
      "features": [
        0.0,
        0.0,
        0.0,
        0.0,
        0.0
      ]
    },
    {
      "line": 34,
      "annotation_type": "@Positive",
      "confidence": 0.5411227345466614,
      "reason": "positive value expected (predicted by ENHANCED_CAUSAL model with 0.541 confidence)",
      "model_type": "enhanced_causal",
      "features": [
        0.0,
        0.0,
        0.0,
        0.0,
        1.0
      ]
    },
    {
      "line": 32,
      "annotation_type": "@Positive",
      "confidence": 0.537455677986145,
      "reason": "positive value expected (predicted by ENHANCED_CAUSAL model with 0.537 confidence)",
      "model_type": "enhanced_causal",
      "features": [
        0.0,
        0.0,
        0.0,
        0.0,
        0.0
      ]
    },
    {
      "line": 31,
      "annotation_type": "@Positive",
      "confidence": 0.5374224781990051,
      "reason": "positive value expected (predicted by ENHANCED_CAUSAL model with 0.537 confidence)",
      "model_type": "enhanced_causal",
      "features": [
        0.0,
        0.0,
        0.0,
        0.0,
        0.0
      ]
    },
    {
      "line": 30,
      "annotation_type": "@Positive",
      "confidence": 0.5373976230621338,
      "reason": "positive value expected (predicted by ENHANCED_CAUSAL model with 0.537 confidence)",
      "model_type": "enhanced_causal",
      "features": [
        0.0,
        0.0,
        0.0,
        0.0,
        0.0
      ]
    },
    {
      "line": 29,
      "annotation_type": "@Positive",
      "confidence": 0.5373822450637817,
      "reason": "positive value expected (predicted by ENHANCED_CAUSAL model with 0.537 confidence)",
      "model_type": "enhanced_causal",
      "features": [
        0.0,
        0.0,
        0.0,
        0.0,
        0.0
      ]
    },
    {
      "line": 28,
      "annotation_type": "@Positive",
      "confidence": 0.5373752117156982,
      "reason": "positive value expected (predicted by ENHANCED_CAUSAL model with 0.537 confidence)",
      "model_type": "enhanced_causal",
      "features": [
        0.0,
        0.0,
        0.0,
        0.0,
        0.0
      ]
    },
    {
      "line": 27,
      "annotation_type": "@Positive",
      "confidence": 0.5373682975769043,
      "reason": "positive value expected (predicted by ENHANCED_CAUSAL model with 0.537 confidence)",
      "model_type": "enhanced_causal",
      "features": [
        0.0,
        0.0,
        0.0,
        0.0,
        0.0
      ]
    },
    {
      "line": 25,
      "annotation_type": "@Positive",
      "confidence": 0.5373538732528687,
      "reason": "positive value expected (predicted by ENHANCED_CAUSAL model with 0.537 confidence)",
      "model_type": "enhanced_causal",
      "features": [
        0.0,
        0.0,
        0.0,
        0.0,
        0.0
      ]
    },
    {
      "line": 24,
      "annotation_type": "@NonNegative",
      "confidence": 0.5392556190490723,
      "reason": "non-negative value expected (predicted by ENHANCED_CAUSAL model with 0.539 confidence)",
      "model_type": "enhanced_causal",
      "features": [
        0.0,
        0.0,
        0.0,
        0.0,
        0.0
      ]
    },
    {
      "line": 23,
      "annotation_type": "@NonNegative",
      "confidence": 0.5366650223731995,
      "reason": "non-negative value expected (predicted by ENHANCED_CAUSAL model with 0.537 confidence)",
      "model_type": "enhanced_causal",
      "features": [
        0.0,
        0.0,
        0.0,
        0.0,
        0.0
      ]
    },
    {
      "line": 22,
      "annotation_type": "@Positive",
      "confidence": 0.5408132076263428,
      "reason": "positive value expected (predicted by ENHANCED_CAUSAL model with 0.541 confidence)",
      "model_type": "enhanced_causal",
      "features": [
        0.0,
        0.0,
        0.0,
        0.0,
        0.0
      ]
    },
    {
      "line": 21,
      "annotation_type": "@NonNegative",
      "confidence": 0.5400129556655884,
      "reason": "non-negative value expected (predicted by ENHANCED_CAUSAL model with 0.540 confidence)",
      "model_type": "enhanced_causal",
      "features": [
        0.0,
        0.0,
        0.0,
        0.0,
        0.0
      ]
    },
    {
      "line": 20,
      "annotation_type": "@NonNegative",
      "confidence": 0.5392963886260986,
      "reason": "non-negative value expected (predicted by ENHANCED_CAUSAL model with 0.539 confidence)",
      "model_type": "enhanced_causal",
      "features": [
        0.0,
        0.0,
        0.0,
        0.0,
        0.0
      ]
    },
    {
      "line": 19,
      "annotation_type": "@Positive",
      "confidence": 0.5375099778175354,
      "reason": "positive value expected (predicted by ENHANCED_CAUSAL model with 0.538 confidence)",
      "model_type": "enhanced_causal",
      "features": [
        0.0,
        0.0,
        0.0,
        0.0,
        0.0
      ]
    },
    {
      "line": 18,
      "annotation_type": "@Positive",
      "confidence": 0.5390588045120239,
      "reason": "positive value expected (predicted by ENHANCED_CAUSAL model with 0.539 confidence)",
      "model_type": "enhanced_causal",
      "features": [
        0.0,
        0.0,
        0.0,
        0.0,
        0.0
      ]
    },
    {
      "line": 17,
      "annotation_type": "@NonNegative",
      "confidence": 0.5400975942611694,
      "reason": "non-negative value expected (predicted by ENHANCED_CAUSAL model with 0.540 confidence)",
      "model_type": "enhanced_causal",
      "features": [
        0.0,
        0.0,
        0.0,
        0.0,
        0.0
      ]
    },
    {
      "line": 16,
      "annotation_type": "@NonNegative",
      "confidence": 0.5393709540367126,
      "reason": "non-negative value expected (predicted by ENHANCED_CAUSAL model with 0.539 confidence)",
      "model_type": "enhanced_causal",
      "features": [
        0.0,
        0.0,
        0.0,
        0.0,
        0.0
      ]
    },
    {
      "line": 15,
      "annotation_type": "@NonNegative",
      "confidence": 0.5365524888038635,
      "reason": "non-negative value expected (predicted by ENHANCED_CAUSAL model with 0.537 confidence)",
      "model_type": "enhanced_causal",
      "features": [
        0.0,
        0.0,
        0.0,
        0.0,
        0.0
      ]
    },
    {
      "line": 14,
      "annotation_type": "@NonNegative",
      "confidence": 0.5391123294830322,
      "reason": "non-negative value expected (predicted by ENHANCED_CAUSAL model with 0.539 confidence)",
      "model_type": "enhanced_causal",
      "features": [
        0.0,
        0.0,
        0.0,
        0.0,
        0.0
      ]
    },
    {
      "line": 13,
      "annotation_type": "@NonNegative",
      "confidence": 0.5365462303161621,
      "reason": "non-negative value expected (predicted by ENHANCED_CAUSAL model with 0.537 confidence)",
      "model_type": "enhanced_causal",
      "features": [
        0.0,
        0.0,
        0.0,
        0.0,
        0.0
      ]
    },
    {
      "line": 12,
      "annotation_type": "@NonNegative",
      "confidence": 0.5353500843048096,
      "reason": "non-negative value expected (predicted by ENHANCED_CAUSAL model with 0.535 confidence)",
      "model_type": "enhanced_causal",
      "features": [
        0.0,
        0.0,
        0.0,
        0.0,
        0.0
      ]
    },
    {
      "line": 11,
      "annotation_type": "@NonNegative",
      "confidence": 0.5402303338050842,
      "reason": "non-negative value expected (predicted by ENHANCED_CAUSAL model with 0.540 confidence)",
      "model_type": "enhanced_causal",
      "features": [
        0.0,
        0.0,
        0.0,
        0.0,
        0.0
      ]
    },
    {
      "line": 10,
      "annotation_type": "@NonNegative",
      "confidence": 0.5395196080207825,
      "reason": "non-negative value expected (predicted by ENHANCED_CAUSAL model with 0.540 confidence)",
      "model_type": "enhanced_causal",
      "features": [
        0.0,
        0.0,
        0.0,
        0.0,
        0.0
      ]
    },
    {
      "line": 9,
      "annotation_type": "@NonNegative",
      "confidence": 0.536540150642395,
      "reason": "non-negative value expected (predicted by ENHANCED_CAUSAL model with 0.537 confidence)",
      "model_type": "enhanced_causal",
      "features": [
        0.0,
        0.0,
        0.0,
        0.0,
        0.0
      ]
    },
    {
      "line": 8,
      "annotation_type": "@NonNegative",
      "confidence": 0.5402889847755432,
      "reason": "non-negative value expected (predicted by ENHANCED_CAUSAL model with 0.540 confidence)",
      "model_type": "enhanced_causal",
      "features": [
        0.0,
        0.0,
        0.0,
        0.0,
        0.0
      ]
    },
    {
      "line": 7,
      "annotation_type": "@NonNegative",
      "confidence": 0.5365532636642456,
      "reason": "non-negative value expected (predicted by ENHANCED_CAUSAL model with 0.537 confidence)",
      "model_type": "enhanced_causal",
      "features": [
        0.0,
        0.0,
        0.0,
        0.0,
        0.0
      ]
    },
    {
      "line": 6,
      "annotation_type": "@NonNegative",
      "confidence": 0.5402979850769043,
      "reason": "non-negative value expected (predicted by ENHANCED_CAUSAL model with 0.540 confidence)",
      "model_type": "enhanced_causal",
      "features": [
        0.0,
        0.0,
        0.0,
        0.0,
        0.0
      ]
    },
    {
      "line": 5,
      "annotation_type": "@Positive",
      "confidence": 0.538139283657074,
      "reason": "positive value expected (predicted by ENHANCED_CAUSAL model with 0.538 confidence)",
      "model_type": "enhanced_causal",
      "features": [
        0.0,
        0.0,
        0.0,
        0.0,
        0.0
      ]
    },
    {
      "line": 4,
      "annotation_type": "@NonNegative",
      "confidence": 0.5395647883415222,
      "reason": "non-negative value expected (predicted by ENHANCED_CAUSAL model with 0.540 confidence)",
      "model_type": "enhanced_causal",
      "features": [
        0.0,
        0.0,
        0.0,
        0.0,
        0.0
      ]
    },
    {
      "line": 3,
      "annotation_type": "@NonNegative",
      "confidence": 0.5365752577781677,
      "reason": "non-negative value expected (predicted by ENHANCED_CAUSAL model with 0.537 confidence)",
      "model_type": "enhanced_causal",
      "features": [
        0.0,
        0.0,
        0.0,
        0.0,
        0.0
      ]
    },
    {
      "line": 2,
      "annotation_type": "@Positive",
      "confidence": 0.5351426005363464,
      "reason": "positive value expected (predicted by ENHANCED_CAUSAL model with 0.535 confidence)",
      "model_type": "enhanced_causal",
      "features": [
        0.0,
        0.0,
        0.0,
        0.0,
        0.0
      ]
    }
  ],
  "timestamp": "2025-09-29 01:36:40"
}