{
  "file": "/home/ubuntu/checker-framework/checker/tests/index/annotated-jdk/src/jdk.internal.vm.ci/share/classes/jdk.vm.ci.hotspot/src/jdk/vm/ci/hotspot/VMIntrinsicMethod.java",
  "predictions": [
    {
      "line": 52,
      "annotation_type": "@NonNegative",
      "confidence": 0.5393510460853577,
      "reason": "non-negative value expected (predicted by ENHANCED_CAUSAL model with 0.539 confidence)",
      "model_type": "enhanced_causal",
      "features": [
        0.0,
        0.0,
        0.0,
        0.0,
        0.0
      ]
    },
    {
      "line": 51,
      "annotation_type": "@Positive",
      "confidence": 0.5389261841773987,
      "reason": "positive value expected (predicted by ENHANCED_CAUSAL model with 0.539 confidence)",
      "model_type": "enhanced_causal",
      "features": [
        0.0,
        0.0,
        0.0,
        0.0,
        1.0
      ]
    },
    {
      "line": 50,
      "annotation_type": "@Positive",
      "confidence": 0.5394107699394226,
      "reason": "positive value expected (predicted by ENHANCED_CAUSAL model with 0.539 confidence)",
      "model_type": "enhanced_causal",
      "features": [
        0.0,
        0.0,
        0.0,
        0.0,
        0.0
      ]
    },
    {
      "line": 48,
      "annotation_type": "@Positive",
      "confidence": 0.5392557382583618,
      "reason": "positive value expected (predicted by ENHANCED_CAUSAL model with 0.539 confidence)",
      "model_type": "enhanced_causal",
      "features": [
        0.0,
        0.0,
        0.0,
        0.0,
        1.0
      ]
    },
    {
      "line": 47,
      "annotation_type": "@Positive",
      "confidence": 0.5393434166908264,
      "reason": "positive value expected (predicted by ENHANCED_CAUSAL model with 0.539 confidence)",
      "model_type": "enhanced_causal",
      "features": [
        0.0,
        0.0,
        0.0,
        0.0,
        0.0
      ]
    },
    {
      "line": 45,
      "annotation_type": "@Positive",
      "confidence": 0.5461597442626953,
      "reason": "positive value expected (predicted by ENHANCED_CAUSAL model with 0.546 confidence)",
      "model_type": "enhanced_causal",
      "features": [
        0.0,
        0.0,
        0.0,
        0.0,
        1.0
      ]
    },
    {
      "line": 44,
      "annotation_type": "@Positive",
      "confidence": 0.5408798456192017,
      "reason": "positive value expected (predicted by ENHANCED_CAUSAL model with 0.541 confidence)",
      "model_type": "enhanced_causal",
      "features": [
        0.0,
        0.0,
        0.0,
        0.0,
        1.0
      ]
    },
    {
      "line": 43,
      "annotation_type": "@Positive",
      "confidence": 0.5391865968704224,
      "reason": "positive value expected (predicted by ENHANCED_CAUSAL model with 0.539 confidence)",
      "model_type": "enhanced_causal",
      "features": [
        0.0,
        0.0,
        0.0,
        0.0,
        0.0
      ]
    },
    {
      "line": 42,
      "annotation_type": "@Positive",
      "confidence": 0.5391370058059692,
      "reason": "positive value expected (predicted by ENHANCED_CAUSAL model with 0.539 confidence)",
      "model_type": "enhanced_causal",
      "features": [
        0.0,
        0.0,
        0.0,
        0.0,
        0.0
      ]
    },
    {
      "line": 40,
      "annotation_type": "@Positive",
      "confidence": 0.543266236782074,
      "reason": "positive value expected (predicted by ENHANCED_CAUSAL model with 0.543 confidence)",
      "model_type": "enhanced_causal",
      "features": [
        0.0,
        0.0,
        0.0,
        0.0,
        0.0
      ]
    },
    {
      "line": 38,
      "annotation_type": "@Positive",
      "confidence": 0.5407937169075012,
      "reason": "positive value expected (predicted by ENHANCED_CAUSAL model with 0.541 confidence)",
      "model_type": "enhanced_causal",
      "features": [
        0.0,
        0.0,
        0.0,
        0.0,
        0.0
      ]
    },
    {
      "line": 36,
      "annotation_type": "@Positive",
      "confidence": 0.5407389402389526,
      "reason": "positive value expected (predicted by ENHANCED_CAUSAL model with 0.541 confidence)",
      "model_type": "enhanced_causal",
      "features": [
        0.0,
        0.0,
        0.0,
        0.0,
        0.0
      ]
    },
    {
      "line": 34,
      "annotation_type": "@Positive",
      "confidence": 0.540684163570404,
      "reason": "positive value expected (predicted by ENHANCED_CAUSAL model with 0.541 confidence)",
      "model_type": "enhanced_causal",
      "features": [
        0.0,
        0.0,
        0.0,
        0.0,
        0.0
      ]
    },
    {
      "line": 32,
      "annotation_type": "@Positive",
      "confidence": 0.5395784378051758,
      "reason": "positive value expected (predicted by ENHANCED_CAUSAL model with 0.540 confidence)",
      "model_type": "enhanced_causal",
      "features": [
        0.0,
        0.0,
        0.0,
        0.0,
        0.0
      ]
    },
    {
      "line": 30,
      "annotation_type": "@Positive",
      "confidence": 0.5374850034713745,
      "reason": "positive value expected (predicted by ENHANCED_CAUSAL model with 0.537 confidence)",
      "model_type": "enhanced_causal",
      "features": [
        0.0,
        0.0,
        0.0,
        0.0,
        0.0
      ]
    },
    {
      "line": 29,
      "annotation_type": "@Positive",
      "confidence": 0.5374486446380615,
      "reason": "positive value expected (predicted by ENHANCED_CAUSAL model with 0.537 confidence)",
      "model_type": "enhanced_causal",
      "features": [
        0.0,
        0.0,
        0.0,
        0.0,
        0.0
      ]
    },
    {
      "line": 28,
      "annotation_type": "@Positive",
      "confidence": 0.5374122858047485,
      "reason": "positive value expected (predicted by ENHANCED_CAUSAL model with 0.537 confidence)",
      "model_type": "enhanced_causal",
      "features": [
        0.0,
        0.0,
        0.0,
        0.0,
        0.0
      ]
    },
    {
      "line": 27,
      "annotation_type": "@Positive",
      "confidence": 0.5373893976211548,
      "reason": "positive value expected (predicted by ENHANCED_CAUSAL model with 0.537 confidence)",
      "model_type": "enhanced_causal",
      "features": [
        0.0,
        0.0,
        0.0,
        0.0,
        0.0
      ]
    },
    {
      "line": 26,
      "annotation_type": "@Positive",
      "confidence": 0.53737872838974,
      "reason": "positive value expected (predicted by ENHANCED_CAUSAL model with 0.537 confidence)",
      "model_type": "enhanced_causal",
      "features": [
        0.0,
        0.0,
        0.0,
        0.0,
        0.0
      ]
    },
    {
      "line": 25,
      "annotation_type": "@Positive",
      "confidence": 0.5373710989952087,
      "reason": "positive value expected (predicted by ENHANCED_CAUSAL model with 0.537 confidence)",
      "model_type": "enhanced_causal",
      "features": [
        0.0,
        0.0,
        0.0,
        0.0,
        0.0
      ]
    },
    {
      "line": 23,
      "annotation_type": "@Positive",
      "confidence": 0.5373554229736328,
      "reason": "positive value expected (predicted by ENHANCED_CAUSAL model with 0.537 confidence)",
      "model_type": "enhanced_causal",
      "features": [
        0.0,
        0.0,
        0.0,
        0.0,
        0.0
      ]
    },
    {
      "line": 22,
      "annotation_type": "@NonNegative",
      "confidence": 0.5392548441886902,
      "reason": "non-negative value expected (predicted by ENHANCED_CAUSAL model with 0.539 confidence)",
      "model_type": "enhanced_causal",
      "features": [
        0.0,
        0.0,
        0.0,
        0.0,
        0.0
      ]
    },
    {
      "line": 21,
      "annotation_type": "@NonNegative",
      "confidence": 0.5366652607917786,
      "reason": "non-negative value expected (predicted by ENHANCED_CAUSAL model with 0.537 confidence)",
      "model_type": "enhanced_causal",
      "features": [
        0.0,
        0.0,
        0.0,
        0.0,
        0.0
      ]
    },
    {
      "line": 20,
      "annotation_type": "@Positive",
      "confidence": 0.5408108830451965,
      "reason": "positive value expected (predicted by ENHANCED_CAUSAL model with 0.541 confidence)",
      "model_type": "enhanced_causal",
      "features": [
        0.0,
        0.0,
        0.0,
        0.0,
        0.0
      ]
    },
    {
      "line": 19,
      "annotation_type": "@NonNegative",
      "confidence": 0.540016770362854,
      "reason": "non-negative value expected (predicted by ENHANCED_CAUSAL model with 0.540 confidence)",
      "model_type": "enhanced_causal",
      "features": [
        0.0,
        0.0,
        0.0,
        0.0,
        0.0
      ]
    },
    {
      "line": 18,
      "annotation_type": "@NonNegative",
      "confidence": 0.5393000245094299,
      "reason": "non-negative value expected (predicted by ENHANCED_CAUSAL model with 0.539 confidence)",
      "model_type": "enhanced_causal",
      "features": [
        0.0,
        0.0,
        0.0,
        0.0,
        0.0
      ]
    },
    {
      "line": 17,
      "annotation_type": "@Positive",
      "confidence": 0.5375171303749084,
      "reason": "positive value expected (predicted by ENHANCED_CAUSAL model with 0.538 confidence)",
      "model_type": "enhanced_causal",
      "features": [
        0.0,
        0.0,
        0.0,
        0.0,
        0.0
      ]
    },
    {
      "line": 16,
      "annotation_type": "@Positive",
      "confidence": 0.5390334129333496,
      "reason": "positive value expected (predicted by ENHANCED_CAUSAL model with 0.539 confidence)",
      "model_type": "enhanced_causal",
      "features": [
        0.0,
        0.0,
        0.0,
        0.0,
        0.0
      ]
    },
    {
      "line": 15,
      "annotation_type": "@NonNegative",
      "confidence": 0.5401082038879395,
      "reason": "non-negative value expected (predicted by ENHANCED_CAUSAL model with 0.540 confidence)",
      "model_type": "enhanced_causal",
      "features": [
        0.0,
        0.0,
        0.0,
        0.0,
        0.0
      ]
    },
    {
      "line": 14,
      "annotation_type": "@NonNegative",
      "confidence": 0.5393882393836975,
      "reason": "non-negative value expected (predicted by ENHANCED_CAUSAL model with 0.539 confidence)",
      "model_type": "enhanced_causal",
      "features": [
        0.0,
        0.0,
        0.0,
        0.0,
        0.0
      ]
    },
    {
      "line": 13,
      "annotation_type": "@NonNegative",
      "confidence": 0.5365501642227173,
      "reason": "non-negative value expected (predicted by ENHANCED_CAUSAL model with 0.537 confidence)",
      "model_type": "enhanced_causal",
      "features": [
        0.0,
        0.0,
        0.0,
        0.0,
        0.0
      ]
    },
    {
      "line": 12,
      "annotation_type": "@NonNegative",
      "confidence": 0.5391215085983276,
      "reason": "non-negative value expected (predicted by ENHANCED_CAUSAL model with 0.539 confidence)",
      "model_type": "enhanced_causal",
      "features": [
        0.0,
        0.0,
        0.0,
        0.0,
        0.0
      ]
    },
    {
      "line": 11,
      "annotation_type": "@NonNegative",
      "confidence": 0.5365431904792786,
      "reason": "non-negative value expected (predicted by ENHANCED_CAUSAL model with 0.537 confidence)",
      "model_type": "enhanced_causal",
      "features": [
        0.0,
        0.0,
        0.0,
        0.0,
        0.0
      ]
    },
    {
      "line": 10,
      "annotation_type": "@NonNegative",
      "confidence": 0.5353389978408813,
      "reason": "non-negative value expected (predicted by ENHANCED_CAUSAL model with 0.535 confidence)",
      "model_type": "enhanced_causal",
      "features": [
        0.0,
        0.0,
        0.0,
        0.0,
        0.0
      ]
    },
    {
      "line": 9,
      "annotation_type": "@NonNegative",
      "confidence": 0.5402551293373108,
      "reason": "non-negative value expected (predicted by ENHANCED_CAUSAL model with 0.540 confidence)",
      "model_type": "enhanced_causal",
      "features": [
        0.0,
        0.0,
        0.0,
        0.0,
        0.0
      ]
    },
    {
      "line": 8,
      "annotation_type": "@NonNegative",
      "confidence": 0.5395323634147644,
      "reason": "non-negative value expected (predicted by ENHANCED_CAUSAL model with 0.540 confidence)",
      "model_type": "enhanced_causal",
      "features": [
        0.0,
        0.0,
        0.0,
        0.0,
        0.0
      ]
    },
    {
      "line": 7,
      "annotation_type": "@NonNegative",
      "confidence": 0.5365488529205322,
      "reason": "non-negative value expected (predicted by ENHANCED_CAUSAL model with 0.537 confidence)",
      "model_type": "enhanced_causal",
      "features": [
        0.0,
        0.0,
        0.0,
        0.0,
        0.0
      ]
    },
    {
      "line": 6,
      "annotation_type": "@NonNegative",
      "confidence": 0.540295422077179,
      "reason": "non-negative value expected (predicted by ENHANCED_CAUSAL model with 0.540 confidence)",
      "model_type": "enhanced_causal",
      "features": [
        0.0,
        0.0,
        0.0,
        0.0,
        0.0
      ]
    },
    {
      "line": 5,
      "annotation_type": "@Positive",
      "confidence": 0.5381680727005005,
      "reason": "positive value expected (predicted by ENHANCED_CAUSAL model with 0.538 confidence)",
      "model_type": "enhanced_causal",
      "features": [
        0.0,
        0.0,
        0.0,
        0.0,
        0.0
      ]
    },
    {
      "line": 4,
      "annotation_type": "@NonNegative",
      "confidence": 0.5395620465278625,
      "reason": "non-negative value expected (predicted by ENHANCED_CAUSAL model with 0.540 confidence)",
      "model_type": "enhanced_causal",
      "features": [
        0.0,
        0.0,
        0.0,
        0.0,
        0.0
      ]
    },
    {
      "line": 3,
      "annotation_type": "@NonNegative",
      "confidence": 0.5365721583366394,
      "reason": "non-negative value expected (predicted by ENHANCED_CAUSAL model with 0.537 confidence)",
      "model_type": "enhanced_causal",
      "features": [
        0.0,
        0.0,
        0.0,
        0.0,
        0.0
      ]
    },
    {
      "line": 2,
      "annotation_type": "@Positive",
      "confidence": 0.5351548790931702,
      "reason": "positive value expected (predicted by ENHANCED_CAUSAL model with 0.535 confidence)",
      "model_type": "enhanced_causal",
      "features": [
        0.0,
        0.0,
        0.0,
        0.0,
        0.0
      ]
    }
  ],
  "timestamp": "2025-09-29 01:36:42"
}